qosst_core/__init__.py
qosst_core/authentication/__init__.py
qosst_core/authentication/base.py
qosst_core/authentication/commands.py
qosst_core/authentication/falcon.py
qosst_core/comm/__init__.py
qosst_core/comm/filters.py
qosst_core/comm/zc.py
qosst_core/commands.py
qosst_core/configuration/__init__.py
qosst_core/configuration/alice.py
qosst_core/configuration/authentication.py
qosst_core/configuration/base.py
qosst_core/configuration/bob.py
qosst_core/configuration/channel.py
qosst_core/configuration/clock.py
qosst_core/configuration/commands.py
qosst_core/configuration/config.example.toml
qosst_core/configuration/config.py
qosst_core/configuration/exceptions.py
qosst_core/configuration/frame.py
qosst_core/configuration/local_oscillator.py
qosst_core/configuration/logs.py
qosst_core/configuration/notifications.py
qosst_core/control_protocol/__init__.py
qosst_core/control_protocol/codes.py
qosst_core/control_protocol/sockets.py
qosst_core/data.py
qosst_core/infos.py
qosst_core/logging.py
qosst_core/modulation/__init__.py
qosst_core/modulation/binomialqam.py
qosst_core/modulation/gaussian.py
qosst_core/modulation/modulation.py
qosst_core/modulation/pcsqam.py
qosst_core/modulation/psk.py
qosst_core/modulation/qam.py
qosst_core/modulation/singlepoint.py
qosst_core/notifications.py
qosst_core/parameters_estimation.py
qosst_core/participant.py
qosst_core/py.typed
qosst_core/schema/__init__.py
qosst_core/schema/detection.py
qosst_core/schema/emission.py
qosst_core/skr_computations.py
qosst_core/utils.py
qosst_core-0.10.1.dist-info/LICENSE
qosst_core-0.10.1.dist-info/METADATA
qosst_core-0.10.1.dist-info/WHEEL
qosst_core-0.10.1.dist-info/entry_points.txt
qosst_core-0.10.1.dist-info/RECORD
