Metadata-Version: 2.1
Name: qosst-core
Version: 0.10.1
Summary: Core submodule of QOSST, containing modules for configuration, control protocol, authentication, modulation and communication filters.
Home-page: https://github.com/qosst
License: GPLv3
Author: Yoann Piétri
Author-email: Yoann.Pietri@lip6.fr
Requires-Python: >=3.9,<3.13
Classifier: Development Status :: 4 - Beta
Classifier: Intended Audience :: Science/Research
Classifier: License :: OSI Approved :: GNU General Public License v3 (GPLv3)
Classifier: License :: Other/Proprietary License
Classifier: Natural Language :: English
Classifier: Operating System :: OS Independent
Classifier: Programming Language :: Python :: 3
Classifier: Programming Language :: Python :: 3.9
Classifier: Programming Language :: Python :: 3.10
Classifier: Programming Language :: Python :: 3.11
Classifier: Programming Language :: Python :: 3.12
Classifier: Topic :: Scientific/Engineering :: Physics
Classifier: Topic :: Security :: Cryptography
Requires-Dist: falcon-digital-signature (>=0.9.2,<0.10.0)
Requires-Dist: importlib-metadata ; python_version < "3.8"
Requires-Dist: numpy (>=1.22.3,<2.0.0)
Requires-Dist: qosst-hal (>=0.10.0,<0.11.0)
Requires-Dist: requests (>=2.27.1,<3.0.0)
Requires-Dist: scipy (>=1.8.0,<2.0.0)
Requires-Dist: toml (>=0.10.2,<0.11.0)
Project-URL: Documentation, https://qosst-core.readthedocs.io/
Project-URL: Repository, https://github.com/qosst/qosst-core
